{
    "MONGO": {
        "LOCAL": {
            "URI": "mongodb://localhost:27017/taxi-check-db",
            "OPTIONS": {
                "useUnifiedTopology": true,
                "useFindAndModify": false,
                "useNewUrlParser": true,
                "socketTimeoutMS": 30000,
                "keepAlive": true,
                "poolSize": 50,
                "autoIndex": false,
                "retryWrites": false
            }
        },
        "REMOTE": {
            "URI": "mongodb+srv://root:root@cluster0.rhqxe.mongodb.net/taxi-check-db",
            "OPTIONS": {
                "useUnifiedTopology": true,
                "useNewUrlParser": true,
                "socketTimeoutMS": 30000,
                "keepAlive": true,
                "poolSize": 50,
                "autoIndex": false,
                "retryWrites": false
            }
        }
    },
    "AFRICAS_TALKING": {
        "apiKey": "3a8e233365437c78fc281374b9848a0943ca02d9a5fb87d21921df571b284cf0",
        "username": "taxicheck"
    },
    "SERVER": {
        "HOSTNAME": "0.0.0.0",
        "PORT": 3000
    },
    "ZEE_PAY": {
        "grant_type": "password",
        "client_id": "108",
        "client_secret": "aAeqAoOLt8mhHX6OkEm6e2scWuCYIXfLwCu9Vlmw",
        "scope": "*",
        "username": "smart@icodegh.com",
        "password": "1Carcheck2021",


        "LIVE_BASE_URL": "https://shop.digitaltermination.com",
        "TEST_BASE_URL": "https://test.digitaltermination.com",
        "JOINER": "/api/custom/transactions/tech-maxx/wallets",
        "AUTH_TOKEN": "/oauth/token",
        "CREDIT_WALLET": "/credit-wallet",
        "DEBIT_WALLET": "/debit-wallet"
    }
}